01_game_of_life/full_adder.sv
module full_adder(a,b,c_in,y,c);

input wire a;
input wire b;
input wire c_in;
output logic y;
output logic c;

always_comb begin
  y = a ^ b ^ c_in;
  c = a & b;
end

endmodule

01_game_of_life/half_adder.sv
module half_adder(a,b,y,c);

input wire a;
input wire b;
output logic y;
output logic c;

always_comb begin
  y = a ^ b;
  c = a & b;
end

endmodule

01_game_of_life/test_adders.sv
`timescale 1ns / 1ps
`default_nettype none

`define SIMULATION

module test_adders;
  logic ena;
  logic [2:0] a;
  logic [2:0] b;
  logic c_in;
  wire [3:0] c;
  

  half_adder UUT(a[0], b[0], c[0], c[1]);
  full_adder UUTF(a[0], b[0], c_in, c[0], c[1]);

  initial begin
    // Collect waveforms
    $dumpfile("adders.vcd");
    $dumpvars(0, UUT);
    $dumpvars(0, UUTF);
    
    $display("a b | c y");
    $display("---------");
    for (int i = 0; i < 4; i = i + 1) begin
      a = i[0];
      b = i[1];
      #1 $display("%1b %1b | %1b %1b", a[0], b[0], c[1], c[0]);
    end

        $display("c a b | c y");
    $display("---------");
    for (int i = 0; i < 8; i = i + 1) begin
      a = i[1];
      b = i[0];
      c_in = i[2];
      #1 $display("%1b %1b %1b | %1b %1b", c_in, a[0], b[0], c[1], c[0]);
    end
        
    $finish;      
    end

endmodule

01_game_of_life/adders.vcd
$date
	Wed Sep 29 18:51:59 2021
$end
$version
	Icarus Verilog
$end
$timescale
	1ps
$end
$scope module test_adders $end
$scope module UUT $end
$var wire 1 ! a $end
$var wire 1 " b $end
$var reg 1 # c $end
$var reg 1 $ y $end
$upscope $end
$upscope $end
$scope module test_adders $end
$scope module UUTF $end
$var wire 1 % a $end
$var wire 1 & b $end
$var wire 1 ' c_in $end
$var reg 1 ( c $end
$var reg 1 ) y $end
$upscope $end
$upscope $end
$enddefinitions $end
#0
$dumpvars
x)
0(
x'
0&
0%
0$
0#
0"
0!
$end
#1000
1$
1!
1%
#2000
1"
1&
0!
0%
#3000
1#
0$
1(
1!
1%
#4000
0#
0(
0)
0"
0&
0!
0%
0'
#5000
1$
1)
1"
1&
#6000
0"
0&
1!
1%
#7000
1#
0$
1(
0)
1"
1&
#8000
0#
0(
1)
0"
0&
0!
0%
1'
#9000
1$
0)
1"
1&
#10000
0"
0&
1!
1%
#11000
1#
0$
1(
1)
1"
1&
