01_game_of_life/full_adder.sv
module full_adder(a,b,c_in,y,c);

input wire a;
input wire b;
input wire c_in;
output logic y;
output logic c;

always_comb begin
  y = a ^ b ^ c_in;
  c = (a & b) | (c_in & a) | (c_in & b);
end

endmodule

01_game_of_life/half_adder.sv
module half_adder(a,b,y,c);

input wire a;
input wire b;
output logic y;
output logic c;

always_comb begin
  y = a ^ b;
  c = a & b;
end

endmodule

01_game_of_life/two_bit_adder.sv
// Use a half-adder and full-adder to create a 2-bit adder
module two_bit_adder(a,b,y,c);

input wire [1:0] a;
input wire [1:0] b;
output logic [1:0] y;
output logic c;
logic c_in;

half_adder half(a[0], b[0], y[0], c_in);
full_adder full(a[1], b[1], c_in, y[1],c);

endmodule

01_game_of_life/test_adders.sv
`timescale 1ns / 1ps
`default_nettype none

`define SIMULATION

module test_adders;
  logic [2:0] a;
  logic [2:0] b;
  logic c_in;
  wire [1:0] c_half;
  wire [1:0] c_full;
  logic [2:0] c_two;
  

  half_adder UUT(a[0], b[0], c_half[0], c_half[1]);
  full_adder UUTF(a[0], b[0], c_in, c_full[0], c_full[1]);
  two_bit_adder UUT2(a[1:0], b[1:0], c_two[1:0], c_two[2]);

  initial begin
    // Collect waveforms
    $dumpfile("adders.vcd");
    $dumpvars(0, UUT);
    $dumpvars(0, UUTF);
    $dumpvars(0, UUT2);
    
    $display("\n\nHalf-Adder: \n");
    $display("a b | c y");
    $display("---------");
    for (int i = 0; i < 4; i = i + 1) begin
      b = i[0];
      a = i[1];
      #1 $display("%1b %1b | %1b %1b", a[0], b[0], c_half[1], c_half[0]);
    end

    $display("\n\nFull Adder: \n");
    $display("c_in  a b | c y");
    $display("----------------");
    for (int i = 0; i < 8; i = i + 1) begin
      b = i[0];
      a = i[1];
      c_in = i[2];
      #1 $display("  %1b   %1b %1b | %1b %1b", c_in, a[0], b[0], c_full[1], c_full[0]);
    end

    $display("\n\n2-bit Adder: \n");
    $display("  a b  | c y ");
    $display("-------------");
    for (int i = 0; i < 16; i = i + 1) begin
      b = i[1:0];
      a = i[3:2];
      #1 $display(" %2b %2b | %1b %2b", a[1:0], b[1:0], c_two[2], c_two[1:0]);
    end
        
    $finish;      
    end

endmodule

01_game_of_life/adders.vcd
$date
	Thu Sep 30 17:19:08 2021
$end
$version
	Icarus Verilog
$end
$timescale
	1ps
$end
$scope module test_adders $end
$scope module UUT $end
$var wire 1 ! a $end
$var wire 1 " b $end
$var reg 1 # c $end
$var reg 1 $ y $end
$upscope $end
$upscope $end
$scope module test_adders $end
$scope module UUTF $end
$var wire 1 % a $end
$var wire 1 & b $end
$var wire 1 ' c_in $end
$var reg 1 ( c $end
$var reg 1 ) y $end
$upscope $end
$upscope $end
$scope module test_adders $end
$scope module UUT2 $end
$var wire 2 * a [1:0] $end
$var wire 2 + b [1:0] $end
$var wire 2 , y [1:0] $end
$var wire 1 - c_in $end
$var wire 1 . c $end
$scope module full $end
$var wire 1 / a $end
$var wire 1 0 b $end
$var wire 1 - c_in $end
$var reg 1 . c $end
$var reg 1 1 y $end
$upscope $end
$scope module half $end
$var wire 1 2 a $end
$var wire 1 3 b $end
$var reg 1 - c $end
$var reg 1 4 y $end
$upscope $end
$upscope $end
$upscope $end
$enddefinitions $end
#0
$dumpvars
04
03
02
01
00
0/
0.
0-
b0 ,
b0 +
b0 *
x)
0(
x'
0&
0%
0$
0#
0"
0!
$end
#1000
b1 ,
14
1$
x(
13
1"
1&
b1 +
#2000
12
03
1!
1%
b1 *
0"
0&
b0 +
#3000
11
1-
b10 ,
04
1#
0$
1(
13
1"
1&
b1 +
#4000
b0 ,
01
0-
02
0#
03
0(
0)
0!
0%
b0 *
0"
0&
b0 +
0'
#5000
b1 ,
14
1$
1)
13
1"
1&
b1 +
#6000
12
03
1!
1%
b1 *
0"
0&
b0 +
#7000
11
1-
b10 ,
04
1#
0$
1(
0)
13
1"
1&
b1 +
#8000
b0 ,
01
0-
02
0#
03
0(
1)
0!
0%
b0 *
0"
0&
b0 +
1'
#9000
b1 ,
14
1$
1(
0)
13
1"
1&
b1 +
#10000
12
03
1!
1%
b1 *
0"
0&
b0 +
#11000
11
1-
b10 ,
04
1#
0$
1)
13
1"
1&
b1 +
#12000
b0 ,
01
0-
02
0#
0(
03
0!
0%
b0 *
0"
0&
b0 +
#13000
b1 ,
14
1$
1(
0)
13
1"
1&
b1 +
#14000
04
b10 ,
11
0$
0(
1)
03
10
0"
0&
b10 +
#15000
b11 ,
14
1$
1(
0)
13
1"
1&
b11 +
#16000
b1 ,
01
12
03
00
1!
1%
b1 *
0"
0&
b0 +
#17000
11
1-
b10 ,
04
1#
0$
1)
13
1"
1&
b1 +
#18000
0-
14
0.
b11 ,
11
0#
1$
0)
03
10
0"
0&
b10 +
#19000
1.
01
1-
b0 ,
04
1#
0$
1)
13
1"
1&
b11 +
#20000
0.
b10 ,
11
0-
02
1/
0#
0(
03
00
0!
0%
b10 *
0"
0&
b0 +
#21000
b11 ,
14
1$
1(
0)
13
1"
1&
b1 +
#22000
04
1.
b0 ,
01
0$
0(
1)
03
10
0"
0&
b10 +
#23000
b1 ,
14
1$
1(
0)
13
1"
1&
b11 +
#24000
0.
b11 ,
11
12
03
00
1!
1%
b11 *
0"
0&
b0 +
#25000
1.
01
1-
b0 ,
04
1#
0$
1)
13
1"
1&
b1 +
#26000
0-
14
b1 ,
01
0#
1$
0)
03
10
0"
0&
b10 +
#27000
11
1-
b10 ,
04
1#
0$
1)
13
1"
1&
b11 +
