01_game_of_life/full_adder.sv
module full_adder(a,b,c_in,y,c);

input wire a;
input wire b;
input wire c_in;
output logic y;
output logic c;

always_comb begin
  y = a ^ b ^ c_in;
  c = a & b;
end

endmodule

01_game_of_life/half_adder.sv
module half_adder(a,b,y,c);

input wire a;
input wire b;
output logic y;
output logic c;

always_comb begin
  y = a ^ b;
  c = a & b;
end

endmodule

01_game_of_life/two_bit_adder.sv
// Use a half-adder and full-adder to create a 2-bit adder
module two_bit_adder(a,b,c,y);

input wire [1:0] a,b;
output logic [1:0] y;
output logic c;
wire c_in;

half_adder half(a[0], b[0], y[0], c_in);
full_adder full(a[1], b[1], c_in, y[1],c);

endmodule

01_game_of_life/three_bit_adder.sv
// Use a 2-bit adder and full-adder to create a 3-bit adder
module three_bit_adder(a,b,c,y);

input wire [2:0] a,b;
output logic [2:0] y;
output logic c;
wire c_in;

two_bit_adder two(a[1:0], b[1:0],c_in, y[1:0]);
full_adder full(a[2], b[2], c_in, y[2],c);

endmodule

01_game_of_life/test_adders.sv
`timescale 1ns / 1ps
`default_nettype none

`define SIMULATION

module test_adders;
  logic [2:0] a;
  logic [2:0] b;
  logic c_in;
  wire [1:0] c_half;
  wire [1:0] c_full;
  logic [2:0] c_two;
  logic [3:0] c_three;
  logic [3:0] sum;
  

  half_adder UUT(a[0], b[0], c_half[0], c_half[1]);
  full_adder UUTF(a[0], b[0], c_in, c_full[0], c_full[1]);
  two_bit_adder UUT2(a[1:0], b[1:0], c_two[1:0], c_two[2]);
  three_bit_adder UUT3(a[2:0], b[2:0], c_three[2:0], c_three[3]);

  initial begin
    // Collect waveforms
    $dumpfile("adders.vcd");
    $dumpvars(0, UUT);
    $dumpvars(0, UUTF);
    $dumpvars(0, UUT2);
    
    $display("\n\nHalf-Adder: \n");
    $display("a b | c y");
    $display("---------");
    for (int i = 0; i < 4; i = i + 1) begin
      b = i[0];
      a = i[1];
      #1 $display("%1b %1b | %1b %1b", a[0], b[0], c_half[1], c_half[0]);
    end

    $display("\n\nFull Adder: \n");
    $display("c_in  a b | c y");
    $display("----------------");
    for (int i = 0; i < 8; i = i + 1) begin
      b = i[0];
      a = i[1];
      c_in = i[2];
      #1 $display("  %1b   %1b %1b | %1b %1b", c_in, a[0], b[0], c_full[1], c_full[0]);
    end

    $display("\n\n2-bit Adder: \n");
    $display("  a b  | c y ");
    $display("-------------");
    for (int i = 0; i < 16; i = i + 1) begin
      b = i[1:0];
      a = i[3:2];
      #1 $display(" %2b %2b | %1b %2b", a[1:0], b[1:0], c_two[2], c_two[1:0]);
    end

    $display("\n3bit adder tested");
    for (int i = 0; i < 128; i = i + 1) begin
      b = i[2:0];
      a = i[6:3];
      sum = a + b;
      #1
      if (c_three !== sum) begin
        $error("%3b + %3b = %4b (expected %4b)", a, b, c_three, sum);
      end

    end
        
    $finish;      
    end

endmodule

01_game_of_life/adders.vcd
$date
	Mon Oct  4 17:19:56 2021
$end
$version
	Icarus Verilog
$end
$timescale
	1ps
$end
$scope module test_adders $end
$scope module UUT $end
$var wire 1 ! a $end
$var wire 1 " b $end
$var reg 1 # c $end
$var reg 1 $ y $end
$upscope $end
$upscope $end
$scope module test_adders $end
$scope module UUTF $end
$var wire 1 % a $end
$var wire 1 & b $end
$var wire 1 ' c_in $end
$var reg 1 ( c $end
$var reg 1 ) y $end
$upscope $end
$upscope $end
$scope module test_adders $end
$scope module UUT2 $end
$var wire 2 * a [1:0] $end
$var wire 2 + b [1:0] $end
$var wire 2 , y [1:0] $end
$var wire 1 - c_in $end
$var wire 1 . c $end
$scope module full $end
$var wire 1 / a $end
$var wire 1 0 b $end
$var wire 1 - c_in $end
$var reg 1 . c $end
$var reg 1 1 y $end
$upscope $end
$scope module half $end
$var wire 1 2 a $end
$var wire 1 3 b $end
$var reg 1 - c $end
$var reg 1 4 y $end
$upscope $end
$upscope $end
$upscope $end
$enddefinitions $end
#0
$dumpvars
04
03
02
01
00
0/
0.
0-
b0 ,
b0 +
b0 *
x)
0(
x'
0&
0%
0$
0#
0"
0!
$end
#1000
b1 ,
14
1$
x(
13
1"
1&
b1 +
#2000
12
03
1!
1%
b1 *
0"
0&
b0 +
#3000
11
1-
b10 ,
04
1#
0$
1(
13
1"
1&
b1 +
#4000
b0 ,
01
0-
02
0#
03
0(
0)
0!
0%
b0 *
0"
0&
b0 +
0'
#5000
b1 ,
14
1$
1)
13
1"
1&
b1 +
#6000
12
03
1!
1%
b1 *
0"
0&
b0 +
#7000
11
1-
b10 ,
04
1#
0$
1(
0)
13
1"
1&
b1 +
#8000
b0 ,
01
0-
02
0#
03
0(
1)
0!
0%
b0 *
0"
0&
b0 +
1'
#9000
b1 ,
14
1$
1(
0)
13
1"
1&
b1 +
#10000
12
03
1!
1%
b1 *
0"
0&
b0 +
#11000
11
1-
b10 ,
04
1#
0$
1)
13
1"
1&
b1 +
#12000
b0 ,
01
0-
02
0#
0(
03
0!
0%
b0 *
0"
0&
b0 +
#13000
b1 ,
14
1$
1(
0)
13
1"
1&
b1 +
#14000
04
b10 ,
11
0$
0(
1)
03
10
0"
0&
b10 +
#15000
b11 ,
14
1$
1(
0)
13
1"
1&
b11 +
#16000
b1 ,
01
12
03
00
1!
1%
b1 *
0"
0&
b0 +
#17000
11
1-
b10 ,
04
1#
0$
1)
13
1"
1&
b1 +
#18000
0-
14
0.
b11 ,
11
0#
1$
0)
03
10
0"
0&
b10 +
#19000
1.
01
1-
b0 ,
04
1#
0$
1)
13
1"
1&
b11 +
#20000
0.
b10 ,
11
0-
02
1/
0#
0(
03
00
0!
0%
b10 *
0"
0&
b0 +
#21000
b11 ,
14
1$
1(
0)
13
1"
1&
b1 +
#22000
04
1.
b0 ,
01
0$
0(
1)
03
10
0"
0&
b10 +
#23000
b1 ,
14
1$
1(
0)
13
1"
1&
b11 +
#24000
0.
b11 ,
11
12
03
00
1!
1%
b11 *
0"
0&
b0 +
#25000
1.
01
1-
b0 ,
04
1#
0$
1)
13
1"
1&
b1 +
#26000
0-
14
b1 ,
01
0#
1$
0)
03
10
0"
0&
b10 +
#27000
11
1-
b10 ,
04
1#
0$
1)
13
1"
1&
b11 +
#28000
b0 ,
01
0-
0.
02
0/
0#
0(
03
00
0!
0%
b0 *
0"
0&
b0 +
#29000
b1 ,
14
1$
1(
0)
13
1"
1&
b1 +
#30000
04
b10 ,
11
0$
0(
1)
03
10
0"
0&
b10 +
#31000
b11 ,
14
1$
1(
0)
13
1"
1&
b11 +
#32000
04
b0 ,
01
0$
0(
1)
03
00
0"
0&
b0 +
#33000
b1 ,
14
1$
1(
0)
13
1"
1&
b1 +
#34000
04
b10 ,
11
0$
0(
1)
03
10
0"
0&
b10 +
#35000
b11 ,
14
1$
1(
0)
13
1"
1&
b11 +
#36000
b1 ,
01
12
03
00
1!
1%
b1 *
0"
0&
b0 +
#37000
11
1-
b10 ,
04
1#
0$
1)
13
1"
1&
b1 +
#38000
0-
14
0.
b11 ,
11
0#
1$
0)
03
10
0"
0&
b10 +
#39000
1.
01
1-
b0 ,
04
1#
0$
1)
13
1"
1&
b11 +
#40000
0-
14
0.
b1 ,
01
0#
1$
0)
03
00
0"
0&
b0 +
#41000
11
1-
b10 ,
04
1#
0$
1)
13
1"
1&
b1 +
#42000
0-
14
0.
b11 ,
11
0#
1$
0)
03
10
0"
0&
b10 +
#43000
1.
01
1-
b0 ,
04
1#
0$
1)
13
1"
1&
b11 +
#44000
0.
b10 ,
11
0-
02
1/
0#
0(
03
00
0!
0%
b10 *
0"
0&
b0 +
#45000
b11 ,
14
1$
1(
0)
13
1"
1&
b1 +
#46000
04
1.
b0 ,
01
0$
0(
1)
03
10
0"
0&
b10 +
#47000
b1 ,
14
1$
1(
0)
13
1"
1&
b11 +
#48000
04
0.
b10 ,
11
0$
0(
1)
03
00
0"
0&
b0 +
#49000
b11 ,
14
1$
1(
0)
13
1"
1&
b1 +
#50000
04
1.
b0 ,
01
0$
0(
1)
03
10
0"
0&
b10 +
#51000
b1 ,
14
1$
1(
0)
13
1"
1&
b11 +
#52000
0.
b11 ,
11
12
03
00
1!
1%
b11 *
0"
0&
b0 +
#53000
1.
01
1-
b0 ,
04
1#
0$
1)
13
1"
1&
b1 +
#54000
0-
14
b1 ,
01
0#
1$
0)
03
10
0"
0&
b10 +
#55000
11
1-
b10 ,
04
1#
0$
1)
13
1"
1&
b11 +
#56000
0.
0-
14
b11 ,
11
0#
1$
0)
03
00
0"
0&
b0 +
#57000
1.
01
1-
b0 ,
04
1#
0$
1)
13
1"
1&
b1 +
#58000
0-
14
b1 ,
01
0#
1$
0)
03
10
0"
0&
b10 +
#59000
11
1-
b10 ,
04
1#
0$
1)
13
1"
1&
b11 +
#60000
b0 ,
01
0-
0.
02
0/
0#
0(
03
00
0!
0%
b0 *
0"
0&
b0 +
#61000
b1 ,
14
1$
1(
0)
13
1"
1&
b1 +
#62000
04
b10 ,
11
0$
0(
1)
03
10
0"
0&
b10 +
#63000
b11 ,
14
1$
1(
0)
13
1"
1&
b11 +
#64000
04
b0 ,
01
0$
0(
1)
03
00
0"
0&
b0 +
#65000
b1 ,
14
1$
1(
0)
13
1"
1&
b1 +
#66000
04
b10 ,
11
0$
0(
1)
03
10
0"
0&
b10 +
#67000
b11 ,
14
1$
1(
0)
13
1"
1&
b11 +
#68000
b1 ,
01
12
03
00
1!
1%
b1 *
0"
0&
b0 +
#69000
11
1-
b10 ,
04
1#
0$
1)
13
1"
1&
b1 +
#70000
0-
14
0.
b11 ,
11
0#
1$
0)
03
10
0"
0&
b10 +
#71000
1.
01
1-
b0 ,
04
1#
0$
1)
13
1"
1&
b11 +
#72000
0-
14
0.
b1 ,
01
0#
1$
0)
03
00
0"
0&
b0 +
#73000
11
1-
b10 ,
04
1#
0$
1)
13
1"
1&
b1 +
#74000
0-
14
0.
b11 ,
11
0#
1$
0)
03
10
0"
0&
b10 +
#75000
1.
01
1-
b0 ,
04
1#
0$
1)
13
1"
1&
b11 +
#76000
0.
b10 ,
11
0-
02
1/
0#
0(
03
00
0!
0%
b10 *
0"
0&
b0 +
#77000
b11 ,
14
1$
1(
0)
13
1"
1&
b1 +
#78000
04
1.
b0 ,
01
0$
0(
1)
03
10
0"
0&
b10 +
#79000
b1 ,
14
1$
1(
0)
13
1"
1&
b11 +
#80000
04
0.
b10 ,
11
0$
0(
1)
03
00
0"
0&
b0 +
#81000
b11 ,
14
1$
1(
0)
13
1"
1&
b1 +
#82000
04
1.
b0 ,
01
0$
0(
1)
03
10
0"
0&
b10 +
#83000
b1 ,
14
1$
1(
0)
13
1"
1&
b11 +
#84000
0.
b11 ,
11
12
03
00
1!
1%
b11 *
0"
0&
b0 +
#85000
1.
01
1-
b0 ,
04
1#
0$
1)
13
1"
1&
b1 +
#86000
0-
14
b1 ,
01
0#
1$
0)
03
10
0"
0&
b10 +
#87000
11
1-
b10 ,
04
1#
0$
1)
13
1"
1&
b11 +
#88000
0.
0-
14
b11 ,
11
0#
1$
0)
03
00
0"
0&
b0 +
#89000
1.
01
1-
b0 ,
04
1#
0$
1)
13
1"
1&
b1 +
#90000
0-
14
b1 ,
01
0#
1$
0)
03
10
0"
0&
b10 +
#91000
11
1-
b10 ,
04
1#
0$
1)
13
1"
1&
b11 +
#92000
b0 ,
01
0-
0.
02
0/
0#
0(
03
00
0!
0%
b0 *
0"
0&
b0 +
#93000
b1 ,
14
1$
1(
0)
13
1"
1&
b1 +
#94000
04
b10 ,
11
0$
0(
1)
03
10
0"
0&
b10 +
#95000
b11 ,
14
1$
1(
0)
13
1"
1&
b11 +
#96000
04
b0 ,
01
0$
0(
1)
03
00
0"
0&
b0 +
#97000
b1 ,
14
1$
1(
0)
13
1"
1&
b1 +
#98000
04
b10 ,
11
0$
0(
1)
03
10
0"
0&
b10 +
#99000
b11 ,
14
1$
1(
0)
13
1"
1&
b11 +
#100000
b1 ,
01
12
03
00
1!
1%
b1 *
0"
0&
b0 +
#101000
11
1-
b10 ,
04
1#
0$
1)
13
1"
1&
b1 +
#102000
0-
14
0.
b11 ,
11
0#
1$
0)
03
10
0"
0&
b10 +
#103000
1.
01
1-
b0 ,
04
1#
0$
1)
13
1"
1&
b11 +
#104000
0-
14
0.
b1 ,
01
0#
1$
0)
03
00
0"
0&
b0 +
#105000
11
1-
b10 ,
04
1#
0$
1)
13
1"
1&
b1 +
#106000
0-
14
0.
b11 ,
11
0#
1$
0)
03
10
0"
0&
b10 +
#107000
1.
01
1-
b0 ,
04
1#
0$
1)
13
1"
1&
b11 +
#108000
0.
b10 ,
11
0-
02
1/
0#
0(
03
00
0!
0%
b10 *
0"
0&
b0 +
#109000
b11 ,
14
1$
1(
0)
13
1"
1&
b1 +
#110000
04
1.
b0 ,
01
0$
0(
1)
03
10
0"
0&
b10 +
#111000
b1 ,
14
1$
1(
0)
13
1"
1&
b11 +
#112000
04
0.
b10 ,
11
0$
0(
1)
03
00
0"
0&
b0 +
#113000
b11 ,
14
1$
1(
0)
13
1"
1&
b1 +
#114000
04
1.
b0 ,
01
0$
0(
1)
03
10
0"
0&
b10 +
#115000
b1 ,
14
1$
1(
0)
13
1"
1&
b11 +
#116000
0.
b11 ,
11
12
03
00
1!
1%
b11 *
0"
0&
b0 +
#117000
1.
01
1-
b0 ,
04
1#
0$
1)
13
1"
1&
b1 +
#118000
0-
14
b1 ,
01
0#
1$
0)
03
10
0"
0&
b10 +
#119000
11
1-
b10 ,
04
1#
0$
1)
13
1"
1&
b11 +
#120000
0.
0-
14
b11 ,
11
0#
1$
0)
03
00
0"
0&
b0 +
#121000
1.
01
1-
b0 ,
04
1#
0$
1)
13
1"
1&
b1 +
#122000
0-
14
b1 ,
01
0#
1$
0)
03
10
0"
0&
b10 +
#123000
11
1-
b10 ,
04
1#
0$
1)
13
1"
1&
b11 +
#124000
b0 ,
01
0-
0.
02
0/
0#
0(
03
00
0!
0%
b0 *
0"
0&
b0 +
#125000
b1 ,
14
1$
1(
0)
13
1"
1&
b1 +
#126000
04
b10 ,
11
0$
0(
1)
03
10
0"
0&
b10 +
#127000
b11 ,
14
1$
1(
0)
13
1"
1&
b11 +
#128000
04
b0 ,
01
0$
0(
1)
03
00
0"
0&
b0 +
#129000
b1 ,
14
1$
1(
0)
13
1"
1&
b1 +
#130000
04
b10 ,
11
0$
0(
1)
03
10
0"
0&
b10 +
#131000
b11 ,
14
1$
1(
0)
13
1"
1&
b11 +
#132000
b1 ,
01
12
03
00
1!
1%
b1 *
0"
0&
b0 +
#133000
11
1-
b10 ,
04
1#
0$
1)
13
1"
1&
b1 +
#134000
0-
14
0.
b11 ,
11
0#
1$
0)
03
10
0"
0&
b10 +
#135000
1.
01
1-
b0 ,
04
1#
0$
1)
13
1"
1&
b11 +
#136000
0-
14
0.
b1 ,
01
0#
1$
0)
03
00
0"
0&
b0 +
#137000
11
1-
b10 ,
04
1#
0$
1)
13
1"
1&
b1 +
#138000
0-
14
0.
b11 ,
11
0#
1$
0)
03
10
0"
0&
b10 +
#139000
1.
01
1-
b0 ,
04
1#
0$
1)
13
1"
1&
b11 +
#140000
0.
b10 ,
11
0-
02
1/
0#
0(
03
00
0!
0%
b10 *
0"
0&
b0 +
#141000
b11 ,
14
1$
1(
0)
13
1"
1&
b1 +
#142000
04
1.
b0 ,
01
0$
0(
1)
03
10
0"
0&
b10 +
#143000
b1 ,
14
1$
1(
0)
13
1"
1&
b11 +
#144000
04
0.
b10 ,
11
0$
0(
1)
03
00
0"
0&
b0 +
#145000
b11 ,
14
1$
1(
0)
13
1"
1&
b1 +
#146000
04
1.
b0 ,
01
0$
0(
1)
03
10
0"
0&
b10 +
#147000
b1 ,
14
1$
1(
0)
13
1"
1&
b11 +
#148000
0.
b11 ,
11
12
03
00
1!
1%
b11 *
0"
0&
b0 +
#149000
1.
01
1-
b0 ,
04
1#
0$
1)
13
1"
1&
b1 +
#150000
0-
14
b1 ,
01
0#
1$
0)
03
10
0"
0&
b10 +
#151000
11
1-
b10 ,
04
1#
0$
1)
13
1"
1&
b11 +
#152000
0.
0-
14
b11 ,
11
0#
1$
0)
03
00
0"
0&
b0 +
#153000
1.
01
1-
b0 ,
04
1#
0$
1)
13
1"
1&
b1 +
#154000
0-
14
b1 ,
01
0#
1$
0)
03
10
0"
0&
b10 +
#155000
11
1-
b10 ,
04
1#
0$
1)
13
1"
1&
b11 +
